{
  "general": {
    "query": "*"
  },
  "banner": {
    "banner": ""
  },
  "resultcount": {
    "total": "89",
    "pagelower": "13",
    "pageupper": "24"
  },
  "menu": [
    {
      "value": "?segment=All;mm=all",
      "label": "Entire Site",
      "path": "?segment=All;mm=all;i=1;m_SiteSection=Entire+Site"
    },
    {
      "value": "?segment=Programs;mm=programs",
      "label": "Education Programs",
      "path": "?segment=Programs;mm=programs;i=1;m_SiteSection=Education+Programs"
    },
    {
      "value": "?segment=Components;mm=components",
      "label": "Education Program Components",
      "path": "?segment=Components;mm=components;i=1;m_SiteSection=Education+Program+Components"
    },
    {
      "value": "?sp_q_33=+%22Common+Core%22;segment=All;sort=segment;mm=core;facet=Components",
      "label": "Common Core",
      "path": "?sp_q_33=+%22Common+Core%22;segment=All;sort=segment;mm=core;facet=Components;i=1;m_SiteSection=Common+Core"
    },
    {
      "value": "?siteSection=Digital and Mobile Learning;segment=Content;mm=digital",
      "label": "Digital & Mobile Learning",
      "path": "?siteSection=Digital and Mobile Learning;segment=Content;mm=digital;i=1;m_SiteSection=Digital+%26+Mobile+Learning"
    },
    {
      "value": "?segment=Products;mm=trade",
      "label": "Popular Books",
      "path": "?segment=Products;mm=trade;i=1;m_SiteSection=Popular+Books"
    },
    {
      "value": "?q1=Kids+%26+Young+Adults;segment=Products;x1=topNavigation;siteSection=Products;mm=youth",
      "label": "Kids & Teens Books",
      "path": "?q1=Kids+%26+Young+Adults;segment=Products;x1=topNavigation;siteSection=Products;mm=youth;i=1;m_SiteSection=Kids+%26+Teens+Books"
    },
    {
      "value": "?segment=Authors;mm=authors",
      "label": "Authors",
      "path": "?segment=Authors;mm=authors;i=1;m_SiteSection=Authors"
    },
    {
      "value": "?segment=Content;mm=content",
      "label": "Articles & Content",
      "path": "?segment=Content;mm=content;i=1;m_SiteSection=Articles+%26+Content"
    }
  ],
  "sort": [],
  "breadcrumb": [
    {
      "value": "*",
      "path": "?i=1;rank=Program_Revenue;segment=Programs",
      "droppath": "?i=1;rank=Program_Revenue;segment=Programs",
      "gotopath": "?i=1;q=*;rank=Program_Revenue;segment=Programs",
      "removepath": "?i=1;rank=Program_Revenue;segment=Programs"
    }
  ],
  "pagination": {
    "previous": "?i=1;q=*;rank=Program_Revenue;segment=Programs",
    "next": "?i=1;page=3;q=*;rank=Program_Revenue;segment=Programs",
    "last": "?i=1;page=8;q=*;rank=Program_Revenue;segment=Programs",
    "viewall": "?all=0;i=1;q=*;rank=Program_Revenue;segment=Programs",
    "pages": [
      {
        "page": "1",
        "link": "?i=1;q=*;rank=Program_Revenue;segment=Programs",
        "selected": "false"
      },
      {
        "page": "2",
        "link": "?i=1;page=2;q=*;rank=Program_Revenue;segment=Programs",
        "selected": "true"
      },
      {
        "page": "3",
        "link": "?i=1;page=3;q=*;rank=Program_Revenue;segment=Programs",
        "selected": "false"
      },
      {
        "page": "4",
        "link": "?i=1;page=4;q=*;rank=Program_Revenue;segment=Programs",
        "selected": "false"
      },
      {
        "page": "5",
        "link": "?i=1;page=5;q=*;rank=Program_Revenue;segment=Programs",
        "selected": "false"
      }
    ]
  },
  "facets": [
    {
      "dummy_value": "for facets switching"
    },
    {
      "key": "grade_dd",
      "displayName": "By grade",
      "values": [
        {
          "value": "Pre-K",
          "selected": "false",
          "count": "5",
          "link": "?i=1;q=*;q1=Pre-K;rank=Program_Revenue;segment=Programs;x1=grade_dd",
          "undolink": ""
        },
        {
          "value": "Kindergarten",
          "selected": "false",
          "count": "29",
          "link": "?i=1;q=*;q1=Kindergarten;rank=Program_Revenue;segment=Programs;x1=grade_dd",
          "undolink": ""
        },
        {
          "value": "1",
          "selected": "false",
          "count": "29",
          "link": "?i=1;q=*;q1=1;rank=Program_Revenue;segment=Programs;x1=grade_dd",
          "undolink": ""
        },
        {
          "value": "2",
          "selected": "false",
          "count": "29",
          "link": "?i=1;q=*;q1=2;rank=Program_Revenue;segment=Programs;x1=grade_dd",
          "undolink": ""
        },
        {
          "value": "3",
          "selected": "false",
          "count": "30",
          "link": "?i=1;q=*;q1=3;rank=Program_Revenue;segment=Programs;x1=grade_dd",
          "undolink": ""
        },
        {
          "value": "4",
          "selected": "false",
          "count": "28",
          "link": "?i=1;q=*;q1=4;rank=Program_Revenue;segment=Programs;x1=grade_dd",
          "undolink": ""
        },
        {
          "value": "5",
          "selected": "false",
          "count": "27",
          "link": "?i=1;q=*;q1=5;rank=Program_Revenue;segment=Programs;x1=grade_dd",
          "undolink": ""
        },
        {
          "value": "6",
          "selected": "false",
          "count": "41",
          "link": "?i=1;q=*;q1=6;rank=Program_Revenue;segment=Programs;x1=grade_dd",
          "undolink": ""
        },
        {
          "value": "7",
          "selected": "false",
          "count": "40",
          "link": "?i=1;q=*;q1=7;rank=Program_Revenue;segment=Programs;x1=grade_dd",
          "undolink": ""
        },
        {
          "value": "8",
          "selected": "false",
          "count": "41",
          "link": "?i=1;q=*;q1=8;rank=Program_Revenue;segment=Programs;x1=grade_dd",
          "undolink": ""
        },
        {
          "value": "9",
          "selected": "false",
          "count": "40",
          "link": "?i=1;q=*;q1=9;rank=Program_Revenue;segment=Programs;x1=grade_dd",
          "undolink": ""
        },
        {
          "value": "10",
          "selected": "false",
          "count": "40",
          "link": "?i=1;q=*;q1=10;rank=Program_Revenue;segment=Programs;x1=grade_dd",
          "undolink": ""
        },
        {
          "value": "11",
          "selected": "false",
          "count": "39",
          "link": "?i=1;q=*;q1=11;rank=Program_Revenue;segment=Programs;x1=grade_dd",
          "undolink": ""
        },
        {
          "value": "12",
          "selected": "false",
          "count": "39",
          "link": "?i=1;q=*;q1=12;rank=Program_Revenue;segment=Programs;x1=grade_dd",
          "undolink": ""
        },
        {
          "value": "College",
          "selected": "false",
          "count": "1",
          "link": "?i=1;q=*;q1=College;rank=Program_Revenue;segment=Programs;x1=grade_dd",
          "undolink": ""
        },
        {
          "value": "Adult",
          "selected": "false",
          "count": "3",
          "link": "?i=1;q=*;q1=Adult;rank=Program_Revenue;segment=Programs;x1=grade_dd",
          "undolink": ""
        }
      ]
    },
    {
      "key": "versionState",
      "displayName": "By State",
      "values": [
        {
          "value": "National",
          "selected": "false",
          "count": "72",
          "link": "?i=1;q=*;q1=National;rank=Program_Revenue;segment=Programs;x1=versionState",
          "undolink": ""
        },
        {
          "value": "Alabama",
          "selected": "false",
          "count": "1",
          "link": "?i=1;q=*;q1=Alabama;rank=Program_Revenue;segment=Programs;x1=versionState",
          "undolink": ""
        },
        {
          "value": "California",
          "selected": "false",
          "count": "7",
          "link": "?i=1;q=*;q1=California;rank=Program_Revenue;segment=Programs;x1=versionState",
          "undolink": ""
        },
        {
          "value": "Florida",
          "selected": "false",
          "count": "3",
          "link": "?i=1;q=*;q1=Florida;rank=Program_Revenue;segment=Programs;x1=versionState",
          "undolink": ""
        },
        {
          "value": "Georgia",
          "selected": "false",
          "count": "1",
          "link": "?i=1;q=*;q1=Georgia;rank=Program_Revenue;segment=Programs;x1=versionState",
          "undolink": ""
        },
        {
          "value": "Illinois",
          "selected": "false",
          "count": "5",
          "link": "?i=1;q=*;q1=Illinois;rank=Program_Revenue;segment=Programs;x1=versionState",
          "undolink": ""
        },
        {
          "value": "Indiana",
          "selected": "false",
          "count": "2",
          "link": "?i=1;q=*;q1=Indiana;rank=Program_Revenue;segment=Programs;x1=versionState",
          "undolink": ""
        },
        {
          "value": "Louisiana",
          "selected": "false",
          "count": "1",
          "link": "?i=1;q=*;q1=Louisiana;rank=Program_Revenue;segment=Programs;x1=versionState",
          "undolink": ""
        },
        {
          "value": "Michigan",
          "selected": "false",
          "count": "2",
          "link": "?i=1;q=*;q1=Michigan;rank=Program_Revenue;segment=Programs;x1=versionState",
          "undolink": ""
        },
        {
          "value": "Missouri",
          "selected": "false",
          "count": "1",
          "link": "?i=1;q=*;q1=Missouri;rank=Program_Revenue;segment=Programs;x1=versionState",
          "undolink": ""
        },
        {
          "value": "Nevada",
          "selected": "false",
          "count": "1",
          "link": "?i=1;q=*;q1=Nevada;rank=Program_Revenue;segment=Programs;x1=versionState",
          "undolink": ""
        },
        {
          "value": "New jersey",
          "selected": "false",
          "count": "1",
          "link": "?i=1;q=*;q1=New+jersey;rank=Program_Revenue;segment=Programs;x1=versionState",
          "undolink": ""
        },
        {
          "value": "New york",
          "selected": "false",
          "count": "2",
          "link": "?i=1;q=*;q1=New+york;rank=Program_Revenue;segment=Programs;x1=versionState",
          "undolink": ""
        },
        {
          "value": "North carolina",
          "selected": "false",
          "count": "1",
          "link": "?i=1;q=*;q1=North+carolina;rank=Program_Revenue;segment=Programs;x1=versionState",
          "undolink": ""
        },
        {
          "value": "Oklahoma",
          "selected": "false",
          "count": "1",
          "link": "?i=1;q=*;q1=Oklahoma;rank=Program_Revenue;segment=Programs;x1=versionState",
          "undolink": ""
        },
        {
          "value": "South carolina",
          "selected": "false",
          "count": "2",
          "link": "?i=1;q=*;q1=South+carolina;rank=Program_Revenue;segment=Programs;x1=versionState",
          "undolink": ""
        },
        {
          "value": "Tennessee",
          "selected": "false",
          "count": "2",
          "link": "?i=1;q=*;q1=Tennessee;rank=Program_Revenue;segment=Programs;x1=versionState",
          "undolink": ""
        },
        {
          "value": "Texas",
          "selected": "false",
          "count": "3",
          "link": "?i=1;q=*;q1=Texas;rank=Program_Revenue;segment=Programs;x1=versionState",
          "undolink": ""
        },
        {
          "value": "Wisconsin",
          "selected": "false",
          "count": "1",
          "link": "?i=1;q=*;q1=Wisconsin;rank=Program_Revenue;segment=Programs;x1=versionState",
          "undolink": ""
        }
      ]
    },
    {
      "key": "t.t2",
      "displayName": "By Category",
      "values": [
        {
          "value": "English Language Learners",
          "selected": "false",
          "count": "1",
          "link": "?i=1;q=*;q1=English+Language+Learners;rank=Program_Revenue;segment=Programs;x1=t.t2",
          "undolink": "",
          "display": "​​true"
        },
        {
          "value": "Intervention",
          "selected": "false",
          "count": "10",
          "link": "?i=1;q=*;q1=Intervention;rank=Program_Revenue;segment=Programs;x1=t.t2",
          "undolink": "",
          "display": "​​true"
        },
        {
          "value": "Math",
          "selected": "false",
          "count": "16",
          "link": "?i=1;q=*;q1=Math;rank=Program_Revenue;segment=Programs;x1=t.t2",
          "undolink": "",
          "display": "​​true"
        },
        {
          "value": "Reading",
          "selected": "false",
          "count": "8",
          "link": "?i=1;q=*;q1=Reading;rank=Program_Revenue;segment=Programs;x1=t.t2",
          "undolink": "",
          "display": "​​true"
        },
        {
          "value": "SCIENCE",
          "selected": "false",
          "count": "13",
          "link": "?i=1;q=*;q1=SCIENCE;rank=Program_Revenue;segment=Programs;x1=t.t2",
          "undolink": "",
          "display": "​​true"
        },
        {
          "value": "adult-education",
          "selected": "false",
          "count": "5",
          "link": "?i=1;q=*;q1=adult-education;rank=Program_Revenue;segment=Programs;x1=t.t2",
          "undolink": "",
          "display": "​​true"
        },
        {
          "value": "early-childhood-pre-k",
          "selected": "false",
          "count": "1",
          "link": "?i=1;q=*;q1=early-childhood-pre-k;rank=Program_Revenue;segment=Programs;x1=t.t2",
          "undolink": "",
          "display": "​​true"
        },
        {
          "value": "literature-and-language-arts",
          "selected": "false",
          "count": "12",
          "link": "?i=1;q=*;q1=literature-and-language-arts;rank=Program_Revenue;segment=Programs;x1=t.t2",
          "undolink": "",
          "display": "​​true"
        },
        {
          "value": "social-studies",
          "selected": "false",
          "count": "16",
          "link": "?i=1;q=*;q1=social-studies;rank=Program_Revenue;segment=Programs;x1=t.t2",
          "undolink": "",
          "display": "​​true"
        },
        {
          "value": "summer-school",
          "selected": "false",
          "count": "2",
          "link": "?i=1;q=*;q1=summer-school;rank=Program_Revenue;segment=Programs;x1=t.t2",
          "undolink": "",
          "display": "​​true"
        },
        {
          "value": "world-languages",
          "selected": "false",
          "count": "5",
          "link": "?i=1;q=*;q1=world-languages;rank=Program_Revenue;segment=Programs;x1=t.t2",
          "undolink": "",
          "display": "false​​"
        }
      ]
    },
    {
      "key": "topic",
      "displayName": "By Topic",
      "values": [
        {
          "value": "Advanced & Electives",
          "selected": "false",
          "count": "7",
          "link": "?i=1;q=*;q1=Advanced+%26+Electives;rank=Program_Revenue;segment=Programs;x1=topic",
          "undolink": "",
          "display": "​​true"
        },
        {
          "value": "Core Curriculum",
          "selected": "false",
          "count": "60",
          "link": "?i=1;q=*;q1=Core+Curriculum;rank=Program_Revenue;segment=Programs;x1=topic",
          "undolink": "",
          "display": "​​true"
        },
        {
          "value": "Enrichment/Support Materials",
          "selected": "false",
          "count": "64",
          "link": "?i=1;q=*;q1=Enrichment~2FSupport+Materials;rank=Program_Revenue;segment=Programs;x1=topic",
          "undolink": "",
          "display": "​​true"
        },
        {
          "value": "Heritage Speakers",
          "selected": "false",
          "count": "16",
          "link": "?i=1;q=*;q1=Heritage+Speakers;rank=Program_Revenue;segment=Programs;x1=topic",
          "undolink": "",
          "display": "​​true"
        },
        {
          "value": "Leveled & Guided Reading",
          "selected": "false",
          "count": "7",
          "link": "?i=1;q=*;q1=Leveled+%26+Guided+Reading;rank=Program_Revenue;segment=Programs;x1=topic",
          "undolink": "",
          "display": "​​true"
        },
        {
          "value": "Plagiarism Prevention",
          "selected": "false",
          "count": "1",
          "link": "?i=1;q=*;q1=Plagiarism+Prevention;rank=Program_Revenue;segment=Programs;x1=topic",
          "undolink": "",
          "display": "​​true"
        },
        {
          "value": "Professional Development",
          "selected": "false",
          "count": "4",
          "link": "?i=1;q=*;q1=Professional+Development;rank=Program_Revenue;segment=Programs;x1=topic",
          "undolink": "",
          "display": "​​true"
        },
        {
          "value": "Speaking & Listening",
          "selected": "false",
          "count": "4",
          "link": "?i=1;q=*;q1=Speaking+%26+Listening;rank=Program_Revenue;segment=Programs;x1=topic",
          "undolink": "",
          "display": "​​true"
        },
        {
          "value": "Summer School/Afterschool",
          "selected": "false",
          "count": "11",
          "link": "?i=1;q=*;q1=Summer+School~2FAfterschool;rank=Program_Revenue;segment=Programs;x1=topic",
          "undolink": "",
          "display": "​​true"
        }
      ]
    }
  ],
  "resultset": {
    "results": [
      {
        "index": "13",
        "url": "index:ProgramFeed?key=PG0398",
        "path": "/shop/education-curriculum/math/secondary-mathematics/hmh-fuse",
        "title": "HMH Fuse: Algebra and Geometry",
        "metaTitle": "hmh-fuse",
        "subtitle": "",
        "price": "",
        "basePrice": "",
        "promoText": "",
        "desc": " The award-winning and revolutionary HMH Fuse&#8482; is a highly interactive and engaging curriculum. HMH Fuse: Algebra 1 Common Core Edition, HMH Fuse: Geometry Common Core Edition, and HMH Fuse: Algebra 2 Common Core Edition enables every student with a personalized learning experience. Students and ... ",
        "body": "The award-winning and revolutionary HMH Fuse&#8482; is a highly interactive and engaging curriculum. HMH Fuse: Algebra 1 Common Core Edition, HMH Fuse: Geometry Common Core Edition, and HMH Fuse: Algebra 2 Common Core Edition enables every student with a personalized learning experience. Students and ...",
        "productCode": "",
        "isbn10Code": "",
        "isbn13Code": "",
        "categoryid": "",
        "groupid": "",
        "publishDate": "No Date",
        "featureddate": "",
        "releasedate": "",
        "copyright": "",
        "segment": "Programs",
        "siteSection": "Education Programs",
        "contentType": "",
        "format": "",
        "publishImprints": "",
        "thumbnailImage": "/~/media/sites/home/education/disciplines/mathematics/secondary/hmh-fuse/pi-hmh-fuse.jpg",
        "lookInsideURL": "",
        "featured": "",
        "downloadURL": "",
        "weeklyRevenue": "",
        "ytdRevenue": "",
        "pages": "",
        "cartonQuantity": "",
        "newRelease": "",
        "reviews": "",
        "excerpts": "",
        "readersguideURL": "",
        "pressreleaseURL": "",
        "videoURL": "",
        "activityguideURL": "",
        "coloringpagesURL": "",
        "eventkitsURL": "",
        "shelftalkerURL": "",
        "sampleURL": "",
        "top": "",
        "status": "",
        "series": "",
        "cpsia": "",
        "chokeHazardIndicator": "",
        "season": "",
        "jacketURL": "/~/media/sites/home/education/disciplines/mathematics/secondary/hmh-fuse/pi-hmh-fuse.jpg",
        "age": "",
        "grade": "9|10|11|12",
        "grade_range": "Grades 9-12,Grades 9-12,Grades 9-12,Grades 9-12",
        "grade_dd": "9|10|11|12",
        "grade_max": "12",
        "grade_min": "9",
        "inventoryStatus": "",
        "productType": "Program",
        "versionState": "",
        "programId": "",
        "programGroupId": "",
        "state": "",
        "restricted": "",
        "salesRestrictionCode": "",
        "componentType": "",
        "topic": "Core Curriculum",
        "versionCopyrightYear": "",
        "id": "PG0398",
        "language": "",
        "versionId": "PG03982012NATIONAL",
        "programName": "",
        "buyNowUrl": "/shop/education-curriculum/math/secondary-mathematics/hmh-fuse/shop-now",
        "programsubtitle": "Math Apps",
        "programgrade": "Grades 6&#8211;12",
        "tables": {
          "authors": [],
          "formats": []
        }
      },
      {
        "index": "14",
        "url": "index:ProgramFeed?key=PG0181",
        "path": "/shop/education-curriculum/world-languages/german/prima",
        "title": "prima",
        "metaTitle": "prima",
        "subtitle": "",
        "price": "",
        "basePrice": "",
        "promoText": "",
        "desc": " prima is an authentic, communicative program for students learning German at Grades 6&#8211;12. With prima , students achieve more through relevant all-German instruction. Teachers benefit from a streamlined approach that allows for flexibility in the ever-changing German classroom. Achieve your ... ",
        "body": "prima is an authentic, communicative program for students learning German at Grades 6&#8211;12. With prima , students achieve more through relevant all-German instruction. Teachers benefit from a streamlined approach that allows for flexibility in the ever-changing German classroom. Achieve your ...",
        "productCode": "",
        "isbn10Code": "",
        "isbn13Code": "",
        "categoryid": "",
        "groupid": "",
        "publishDate": "No Date",
        "featureddate": "",
        "releasedate": "",
        "copyright": "",
        "segment": "Programs",
        "siteSection": "Education Programs",
        "contentType": "",
        "format": "",
        "publishImprints": "",
        "thumbnailImage": "/~/media/sites/home/education/disciplines/world-languages/german/prima/prima-pi-new.jpg",
        "lookInsideURL": "",
        "featured": "",
        "downloadURL": "",
        "weeklyRevenue": "",
        "ytdRevenue": "",
        "pages": "",
        "cartonQuantity": "",
        "newRelease": "",
        "reviews": "",
        "excerpts": "",
        "readersguideURL": "",
        "pressreleaseURL": "",
        "videoURL": "",
        "activityguideURL": "",
        "coloringpagesURL": "",
        "eventkitsURL": "",
        "shelftalkerURL": "",
        "sampleURL": "http://forms.hmhco.com/forms/index.php?form=vs&amp;code=i.14deutsch",
        "top": "",
        "status": "",
        "series": "",
        "cpsia": "",
        "chokeHazardIndicator": "",
        "season": "",
        "jacketURL": "/~/media/sites/home/education/disciplines/world-languages/german/prima/prima-pi-new.jpg",
        "age": "",
        "grade": "6|7|8|9|10|11|12",
        "grade_range": "Grades 6-8,Grades 6-8,Grades 6-8,Grades 9-12,Grades 9-12,Grades 9-12,Grades 9-12",
        "grade_dd": "6|7|8|9|10|11|12",
        "grade_max": "12",
        "grade_min": "6",
        "inventoryStatus": "",
        "productType": "Program",
        "versionState": "",
        "programId": "",
        "programGroupId": "",
        "state": "",
        "restricted": "",
        "salesRestrictionCode": "",
        "componentType": "",
        "topic": "Enrichment/Support Materials,Core Curriculum",
        "versionCopyrightYear": "",
        "id": "PG0181",
        "language": "",
        "versionId": "PG01812014NATIONAL",
        "programName": "",
        "buyNowUrl": "/shop/education-curriculum/world-languages/german/prima/shop-now",
        "programsubtitle": "Middle and High School German Curriculum",
        "programgrade": "Grades 6&#8211;12",
        "tables": {
          "authors": [],
          "formats": []
        }
      },
      {
        "index": "15",
        "url": "index:ProgramFeed?key=PG0042",
        "path": "/shop/education-curriculum/science/secondary-science/earth-science",
        "title": "Holt McDougal Earth Science",
        "metaTitle": "earth-science",
        "subtitle": "",
        "price": "",
        "basePrice": "",
        "promoText": "",
        "desc": " Encourage the mastery of Earth science skills with the Earth science curriculum that emphasizes inquiry, critical thinking, and problem solving. Holt McDougal Earth Science provides ongoing support for reading, resources for differentiated instruction, engaging multimedia, and online resources. ... ",
        "body": "Encourage the mastery of Earth science skills with the Earth science curriculum that emphasizes inquiry, critical thinking, and problem solving. Holt McDougal Earth Science provides ongoing support for reading, resources for differentiated instruction, engaging multimedia, and online resources. ...",
        "productCode": "",
        "isbn10Code": "",
        "isbn13Code": "",
        "categoryid": "",
        "groupid": "",
        "publishDate": "No Date",
        "featureddate": "",
        "releasedate": "",
        "copyright": "",
        "segment": "Programs",
        "siteSection": "Education Programs",
        "contentType": "",
        "format": "",
        "publishImprints": "",
        "thumbnailImage": "/~/media/sites/home/education/disciplines/science/secondary/earth-science/pi-hm-earth-science-131114.jpg",
        "lookInsideURL": "",
        "featured": "",
        "downloadURL": "",
        "weeklyRevenue": "",
        "ytdRevenue": "",
        "pages": "",
        "cartonQuantity": "",
        "newRelease": "",
        "reviews": "",
        "excerpts": "",
        "readersguideURL": "",
        "pressreleaseURL": "",
        "videoURL": "",
        "activityguideURL": "",
        "coloringpagesURL": "",
        "eventkitsURL": "",
        "shelftalkerURL": "",
        "sampleURL": "http://forms.hmhco.com/virtualsampling/vs-registration.php?code=hmdesci",
        "top": "",
        "status": "",
        "series": "",
        "cpsia": "",
        "chokeHazardIndicator": "",
        "season": "",
        "jacketURL": "/~/media/sites/home/education/disciplines/science/secondary/earth-science/pi-hm-earth-science-131114.jpg",
        "age": "",
        "grade": "6|7|8|9|10|11|12",
        "grade_range": "Grades 6-8,Grades 6-8,Grades 6-8,Grades 9-12,Grades 9-12,Grades 9-12,Grades 9-12",
        "grade_dd": "6|7|8|9|10|11|12",
        "grade_max": "12",
        "grade_min": "6",
        "inventoryStatus": "",
        "productType": "Program",
        "versionState": "",
        "programId": "",
        "programGroupId": "",
        "state": "",
        "restricted": "",
        "salesRestrictionCode": "",
        "componentType": "",
        "topic": "Heritage Speakers,Enrichment/Support Materials,Core Curriculum",
        "versionCopyrightYear": "",
        "id": "PG0042",
        "language": "",
        "versionId": "PG00422010NATIONAL",
        "programName": "",
        "buyNowUrl": "/shop/education-curriculum/science/secondary-science/earth-science/shop-now",
        "programsubtitle": "Earth Science Curriculum",
        "programgrade": "Grades 9&#8211;12",
        "tables": {
          "authors": [],
          "formats": []
        }
      },
      {
        "index": "16",
        "url": "index:ProgramFeed?key=PG0142",
        "path": "/shop/education-curriculum/science/elementary-science/sciencefusion",
        "title": "ScienceFusion",
        "metaTitle": "sciencefusion",
        "subtitle": "",
        "price": "",
        "basePrice": "",
        "promoText": "",
        "desc": " ScienceFusion is a state-of-the-art science program designed for building inquiry, STEM, and optimized for learning in the classroom, at home, on a laptop, a tablet, or using a science textbook. The digital curriculum, virtual labs and hands-on activities, and write-in science textbook develops ... ",
        "body": "ScienceFusion is a state-of-the-art science program designed for building inquiry, STEM, and optimized for learning in the classroom, at home, on a laptop, a tablet, or using a science textbook. The digital curriculum, virtual labs and hands-on activities, and write-in science textbook develops ...",
        "productCode": "",
        "isbn10Code": "",
        "isbn13Code": "",
        "categoryid": "",
        "groupid": "",
        "publishDate": "No Date",
        "featureddate": "",
        "releasedate": "",
        "copyright": "",
        "segment": "Programs",
        "siteSection": "Education Programs",
        "contentType": "",
        "format": "",
        "publishImprints": "",
        "thumbnailImage": "/~/media/sites/home/education/disciplines/science/elementary/sciencefusion-homeschool/pi-sciencefusion.jpg",
        "lookInsideURL": "",
        "featured": "",
        "downloadURL": "",
        "weeklyRevenue": "",
        "ytdRevenue": "",
        "pages": "",
        "cartonQuantity": "",
        "newRelease": "",
        "reviews": "",
        "excerpts": "",
        "readersguideURL": "",
        "pressreleaseURL": "",
        "videoURL": "",
        "activityguideURL": "",
        "coloringpagesURL": "",
        "eventkitsURL": "",
        "shelftalkerURL": "",
        "sampleURL": "http://forms.hmhco.com/forms/index.php?form=vs&amp;code=nl12scif",
        "top": "",
        "status": "",
        "series": "",
        "cpsia": "",
        "chokeHazardIndicator": "",
        "season": "",
        "jacketURL": "/~/media/sites/home/education/disciplines/science/elementary/sciencefusion-homeschool/pi-sciencefusion.jpg",
        "age": "",
        "grade": "1|2|3|4|5|6|7|8|14",
        "grade_range": "Grades 1-2,Grades 1-2,Grades 3-5,Grades 3-5,Grades 3-5,Grades 6-8,Grades ...",
        "grade_dd": "1|2|3|4|5|6|7|8|Kindergarten",
        "grade_max": "8",
        "grade_min": "Kindergarten",
        "inventoryStatus": "",
        "productType": "Program",
        "versionState": "",
        "programId": "",
        "programGroupId": "",
        "state": "",
        "restricted": "",
        "salesRestrictionCode": "",
        "componentType": "",
        "topic": "Enrichment/Support Materials,Core Curriculum",
        "versionCopyrightYear": "",
        "id": "PG0142",
        "language": "",
        "versionId": "PG01422012NATIONAL",
        "programName": "",
        "buyNowUrl": "/shop/education-curriculum/science/elementary-science/sciencefusion/shop-now",
        "programsubtitle": "More Than Just a Science Textbook",
        "programgrade": "Grades K&#8211;8",
        "tables": {
          "authors": [],
          "formats": []
        }
      },
      {
        "index": "17",
        "url": "index:ProgramFeed?key=PG0035",
        "path": "/shop/education-curriculum/science/secondary-science/environmental-science",
        "title": "Environmental Science",
        "metaTitle": "environmental-science",
        "subtitle": "",
        "price": "",
        "basePrice": "",
        "promoText": "",
        "desc": " Engaging and timely, Environmental Science is specifically designed to appeal to high school students with varied interests and learning abilities. Balanced coverage of environmental topics including ecology, Earth science, health, and policy issues, is a hallmark of the program. An unparalleled ... ",
        "body": "Engaging and timely, Environmental Science is specifically designed to appeal to high school students with varied interests and learning abilities. Balanced coverage of environmental topics including ecology, Earth science, health, and policy issues, is a hallmark of the program. An unparalleled ...",
        "productCode": "",
        "isbn10Code": "",
        "isbn13Code": "",
        "categoryid": "",
        "groupid": "",
        "publishDate": "No Date",
        "featureddate": "",
        "releasedate": "",
        "copyright": "",
        "segment": "Programs",
        "siteSection": "Education Programs",
        "contentType": "",
        "format": "",
        "publishImprints": "",
        "thumbnailImage": "/~/media/sites/home/education/disciplines/science/secondary/environmental-science/pi-environmental-science.jpg",
        "lookInsideURL": "",
        "featured": "",
        "downloadURL": "",
        "weeklyRevenue": "",
        "ytdRevenue": "",
        "pages": "",
        "cartonQuantity": "",
        "newRelease": "",
        "reviews": "",
        "excerpts": "",
        "readersguideURL": "",
        "pressreleaseURL": "",
        "videoURL": "",
        "activityguideURL": "",
        "coloringpagesURL": "",
        "eventkitsURL": "",
        "shelftalkerURL": "",
        "sampleURL": "http://forms.hmhco.com/forms/index.php?form=vs&amp;code=nl13hmesci",
        "top": "",
        "status": "",
        "series": "",
        "cpsia": "",
        "chokeHazardIndicator": "",
        "season": "",
        "jacketURL": "/~/media/sites/home/education/disciplines/science/secondary/environmental-science/pi-environmental-science.jpg",
        "age": "",
        "grade": "9|10|11|12",
        "grade_range": "Grades 9-12,Grades 9-12,Grades 9-12,Grades 9-12",
        "grade_dd": "9|10|11|12",
        "grade_max": "12",
        "grade_min": "9",
        "inventoryStatus": "",
        "productType": "Program",
        "versionState": "",
        "programId": "",
        "programGroupId": "",
        "state": "",
        "restricted": "",
        "salesRestrictionCode": "",
        "componentType": "",
        "topic": "Heritage Speakers,Advanced &amp; Electives,Speaking &amp; ...",
        "versionCopyrightYear": "",
        "id": "PG0035",
        "language": "",
        "versionId": "PG00352008NATIONAL|PG00352013NATIONAL",
        "programName": "",
        "buyNowUrl": "/shop/education-curriculum/science/secondary-science/environmental-science/shop-now",
        "programsubtitle": "Environmental Science Textbook and Digital Program",
        "programgrade": "Grades 9&#8211;12",
        "tables": {
          "authors": [],
          "formats": []
        }
      },
      {
        "index": "18",
        "url": "index:ProgramFeed?key=PG0105",
        "path": "/shop/education-curriculum/science/secondary-science/modern-chemistry",
        "title": "Modern Chemistry",
        "metaTitle": "modern-chemistry",
        "subtitle": "",
        "price": "",
        "basePrice": "",
        "promoText": "",
        "desc": " Holt McDougal Modern Chemistry &#0169; 2012 is a comprehensive high school chemistry textbook and digital program that presents a balanced and engaging approach to conceptual and problem-solving instruction. Designed to accommodate a wide range of student abilities within a general high school ... ",
        "body": "Holt McDougal Modern Chemistry &#0169; 2012 is a comprehensive high school chemistry textbook and digital program that presents a balanced and engaging approach to conceptual and problem-solving instruction. Designed to accommodate a wide range of student abilities within a general high school ...",
        "productCode": "",
        "isbn10Code": "",
        "isbn13Code": "",
        "categoryid": "",
        "groupid": "",
        "publishDate": "No Date",
        "featureddate": "",
        "releasedate": "",
        "copyright": "",
        "segment": "Programs",
        "siteSection": "Education Programs",
        "contentType": "",
        "format": "",
        "publishImprints": "",
        "thumbnailImage": "/~/media/sites/home/education/disciplines/science/secondary/modern-chemistry/pi-modern-chemistry.jpg",
        "lookInsideURL": "",
        "featured": "",
        "downloadURL": "",
        "weeklyRevenue": "",
        "ytdRevenue": "",
        "pages": "",
        "cartonQuantity": "",
        "newRelease": "",
        "reviews": "",
        "excerpts": "",
        "readersguideURL": "",
        "pressreleaseURL": "",
        "videoURL": "",
        "activityguideURL": "",
        "coloringpagesURL": "",
        "eventkitsURL": "",
        "shelftalkerURL": "",
        "sampleURL": "http://forms.hmhco.com/forms/index.php?form=vs&amp;code=nachem12",
        "top": "",
        "status": "",
        "series": "",
        "cpsia": "",
        "chokeHazardIndicator": "",
        "season": "",
        "jacketURL": "/~/media/sites/home/education/disciplines/science/secondary/modern-chemistry/pi-modern-chemistry.jpg",
        "age": "",
        "grade": "9|10|11|12",
        "grade_range": "Grades 9-12,Grades 9-12,Grades 9-12,Grades 9-12",
        "grade_dd": "9|10|11|12",
        "grade_max": "12",
        "grade_min": "9",
        "inventoryStatus": "",
        "productType": "Program",
        "versionState": "",
        "programId": "",
        "programGroupId": "",
        "state": "",
        "restricted": "",
        "salesRestrictionCode": "",
        "componentType": "",
        "topic": "Heritage Speakers,Enrichment/Support Materials,Core Curriculum",
        "versionCopyrightYear": "",
        "id": "PG0105",
        "language": "",
        "versionId": "PG01052009NATIONAL|PG01052006NATIONAL|PG01052012NATIONAL",
        "programName": "",
        "buyNowUrl": "/shop/education-curriculum/science/secondary-science/modern-chemistry/shop-now",
        "programsubtitle": "Chemistry Textbook and Digital Program",
        "programgrade": "Grades 9&#8211;12",
        "tables": {
          "authors": [],
          "formats": []
        }
      },
      {
        "index": "19",
        "url": "index:ProgramFeed?key=PG0028",
        "path": "/shop/education-curriculum/social-studies/elementary-social-studies/harcourt-social-studies",
        "title": "Harcourt Social Studies",
        "metaTitle": "harcourt-social-studies",
        "subtitle": "",
        "price": "",
        "basePrice": "",
        "promoText": "",
        "desc": " Harcourt Social Studies is a comprehensive K&#8211;5 curriculum solution designed to engage and motivate every student. Through the stories of the intriguing people, exciting places, and fascinating events that make social studies relevant to their lives, students gain a global perspective. They also ... ",
        "body": "Harcourt Social Studies is a comprehensive K&#8211;5 curriculum solution designed to engage and motivate every student. Through the stories of the intriguing people, exciting places, and fascinating events that make social studies relevant to their lives, students gain a global perspective. They also ...",
        "productCode": "",
        "isbn10Code": "",
        "isbn13Code": "",
        "categoryid": "",
        "groupid": "",
        "publishDate": "No Date",
        "featureddate": "",
        "releasedate": "",
        "copyright": "",
        "segment": "Programs",
        "siteSection": "Education Programs",
        "contentType": "",
        "format": "",
        "publishImprints": "",
        "thumbnailImage": "/~/media/sites/home/education/disciplines/social-studies/harcourt-social-studies/pi-harcourt-social-studies.jpg",
        "lookInsideURL": "",
        "featured": "",
        "downloadURL": "",
        "weeklyRevenue": "",
        "ytdRevenue": "",
        "pages": "",
        "cartonQuantity": "",
        "newRelease": "",
        "reviews": "",
        "excerpts": "",
        "readersguideURL": "",
        "pressreleaseURL": "",
        "videoURL": "",
        "activityguideURL": "",
        "coloringpagesURL": "",
        "eventkitsURL": "",
        "shelftalkerURL": "",
        "sampleURL": "http://forms.hmhco.com/forms/index.php?form=vs&amp;code=hssk6",
        "top": "",
        "status": "",
        "series": "",
        "cpsia": "",
        "chokeHazardIndicator": "",
        "season": "",
        "jacketURL": "/~/media/sites/home/education/disciplines/social-studies/harcourt-social-studies/pi-harcourt-social-studies.jpg",
        "age": "",
        "grade": "1|2|3|4|5|6|7|8|13|14",
        "grade_range": "Grades 1-2,Grades 1-2,Grades 3-5,Grades 3-5,Grades 3-5,Grades 6-8,Grades ...",
        "grade_dd": "1|2|3|4|5|6|7|8|Pre-K|Kindergarten",
        "grade_max": "8",
        "grade_min": "Pre-K",
        "inventoryStatus": "",
        "productType": "Program",
        "versionState": "",
        "programId": "",
        "programGroupId": "",
        "state": "",
        "restricted": "",
        "salesRestrictionCode": "",
        "componentType": "",
        "topic": "Enrichment/Support Materials,Core Curriculum",
        "versionCopyrightYear": "",
        "id": "PG0028",
        "language": "",
        "versionId": "PG00282007NATIONAL|PG00282008NATIONAL|PG00282010NATIONAL|PG00282012NATIONAL|P...",
        "programName": "",
        "buyNowUrl": "/shop/education-curriculum/social-studies/elementary-social-studies/harcourt-social-studies/shop-now",
        "programsubtitle": "Elementary Social Studies Curriculum",
        "programgrade": "Grades K&#8211;5",
        "tables": {
          "authors": [],
          "formats": []
        }
      },
      {
        "index": "20",
        "url": "index:ProgramFeed?key=PG0070",
        "path": "/shop/education-curriculum/math/secondary-mathematics/on-core-mathematics",
        "title": "On Core Mathematics",
        "metaTitle": "on-core-mathematics",
        "subtitle": "",
        "price": "",
        "basePrice": "",
        "promoText": "",
        "desc": " On Core Mathematics for Grades 6&#8211;12 is a complete program for transitioning to the Common Core State Standards with interactive, real-world applications that help students deepen their understanding of crucial math concepts, while addressing the Common Core Curriculum and the Standards for ... ",
        "body": "On Core Mathematics for Grades 6&#8211;12 is a complete program for transitioning to the Common Core State Standards with interactive, real-world applications that help students deepen their understanding of crucial math concepts, while addressing the Common Core Curriculum and the Standards for ...",
        "productCode": "",
        "isbn10Code": "",
        "isbn13Code": "",
        "categoryid": "",
        "groupid": "",
        "publishDate": "No Date",
        "featureddate": "",
        "releasedate": "",
        "copyright": "",
        "segment": "Programs",
        "siteSection": "Education Programs",
        "contentType": "",
        "format": "",
        "publishImprints": "",
        "thumbnailImage": "/~/media/sites/home/education/disciplines/mathematics/elementary/on-core-math/pi-on-core-math.jpg",
        "lookInsideURL": "",
        "featured": "",
        "downloadURL": "",
        "weeklyRevenue": "",
        "ytdRevenue": "",
        "pages": "",
        "cartonQuantity": "",
        "newRelease": "",
        "reviews": "",
        "excerpts": "",
        "readersguideURL": "",
        "pressreleaseURL": "",
        "videoURL": "",
        "activityguideURL": "",
        "coloringpagesURL": "",
        "eventkitsURL": "",
        "shelftalkerURL": "",
        "sampleURL": "/shop/education-curriculum/math/secondary-mathematics/on-core-mathematics/virtual-sampling",
        "top": "",
        "status": "",
        "series": "",
        "cpsia": "",
        "chokeHazardIndicator": "",
        "season": "",
        "jacketURL": "/~/media/sites/home/education/disciplines/mathematics/elementary/on-core-math/pi-on-core-math.jpg",
        "age": "",
        "grade": "1|2|3|4|5|6|7|8|9|10|11|12|14",
        "grade_range": "Grades 1-2,Grades 1-2,Grades 3-5,Grades 3-5,Grades 3-5,Grades 6-8,Grades ...",
        "grade_dd": "1|2|3|4|5|6|7|8|9|10|11|12|Kindergarten",
        "grade_max": "12",
        "grade_min": "Kindergarten",
        "inventoryStatus": "",
        "productType": "Program",
        "versionState": "",
        "programId": "",
        "programGroupId": "",
        "state": "",
        "restricted": "",
        "salesRestrictionCode": "",
        "componentType": "",
        "topic": "Summer School/Afterschool,Enrichment/Support Materials,Core Curriculum",
        "versionCopyrightYear": "",
        "id": "PG0070",
        "language": "",
        "versionId": "PG00702012NATIONAL",
        "programName": "",
        "buyNowUrl": "/shop/education-curriculum/math/secondary-mathematics/on-core-mathematics/shop-now",
        "programsubtitle": "Common Core Math Curriculum",
        "programgrade": "Grades 6&#8211;12",
        "tables": {
          "authors": [],
          "formats": []
        }
      },
      {
        "index": "21",
        "url": "index:ProgramFeed?key=PG0074",
        "path": "/shop/education-curriculum/math/elementary-mathematics/houghton-mifflin-math",
        "title": "Houghton Mifflin Math",
        "metaTitle": "houghton-mifflin-math",
        "subtitle": "",
        "price": "",
        "basePrice": "",
        "promoText": "",
        "desc": " Houghton Mifflin Math is an elementary-level mathematics curriculum geared towards every level of learning with focused lessons, rich problem solving, and dynamic real-world connections, providing unmatched resources for a new generation of math learners. Engage and challenge students with ... ",
        "body": "Houghton Mifflin Math is an elementary-level mathematics curriculum geared towards every level of learning with focused lessons, rich problem solving, and dynamic real-world connections, providing unmatched resources for a new generation of math learners. Engage and challenge students with ...",
        "productCode": "",
        "isbn10Code": "",
        "isbn13Code": "",
        "categoryid": "",
        "groupid": "",
        "publishDate": "No Date",
        "featureddate": "",
        "releasedate": "",
        "copyright": "",
        "segment": "Programs",
        "siteSection": "Education Programs",
        "contentType": "",
        "format": "",
        "publishImprints": "",
        "thumbnailImage": "/~/media/sites/home/education/disciplines/mathematics/elementary/houghton-mifflin-math/pi-hm-math.jpg",
        "lookInsideURL": "",
        "featured": "",
        "downloadURL": "",
        "weeklyRevenue": "",
        "ytdRevenue": "",
        "pages": "",
        "cartonQuantity": "",
        "newRelease": "",
        "reviews": "",
        "excerpts": "",
        "readersguideURL": "",
        "pressreleaseURL": "",
        "videoURL": "",
        "activityguideURL": "",
        "coloringpagesURL": "",
        "eventkitsURL": "",
        "shelftalkerURL": "",
        "sampleURL": "",
        "top": "",
        "status": "",
        "series": "",
        "cpsia": "",
        "chokeHazardIndicator": "",
        "season": "",
        "jacketURL": "/~/media/sites/home/education/disciplines/mathematics/elementary/houghton-mifflin-math/pi-hm-math.jpg",
        "age": "",
        "grade": "1|2|3|4|5|6|7|8|14",
        "grade_range": "Grades 1-2,Grades 1-2,Grades 3-5,Grades 3-5,Grades 3-5,Grades 6-8,Grades ...",
        "grade_dd": "1|2|3|4|5|6|7|8|Kindergarten",
        "grade_max": "8",
        "grade_min": "Kindergarten",
        "inventoryStatus": "",
        "productType": "Program",
        "versionState": "",
        "programId": "",
        "programGroupId": "",
        "state": "",
        "restricted": "",
        "salesRestrictionCode": "",
        "componentType": "",
        "topic": "Enrichment/Support Materials,Core Curriculum",
        "versionCopyrightYear": "",
        "id": "PG0074",
        "language": "",
        "versionId": "PG00742007NATIONAL",
        "programName": "",
        "buyNowUrl": "/shop/education-curriculum/math/elementary-mathematics/houghton-mifflin-math/shop-now",
        "programsubtitle": "Elementary Math Curriculum",
        "programgrade": "Grades K&#8211;6",
        "tables": {
          "authors": [],
          "formats": []
        }
      },
      {
        "index": "22",
        "url": "index:ProgramFeed?key=PG0011",
        "path": "/shop/education-curriculum/math/secondary-mathematics/big-ideas-math",
        "title": "Big Ideas Math",
        "metaTitle": "big-ideas-math",
        "subtitle": "",
        "price": "",
        "basePrice": "",
        "promoText": "",
        "desc": " Big Ideas Math &#0174; is the first complete middle and high school curriculum written to the Common Core State Standards and uses the Standards for Mathematical Practice as a foundation. Big Ideas Math in your classroom Innovative technology package for the 21st century classroom . Focuses on Rigor ... ",
        "body": "Big Ideas Math &#0174; is the first complete middle and high school curriculum written to the Common Core State Standards and uses the Standards for Mathematical Practice as a foundation. Big Ideas Math in your classroom Innovative technology package for the 21st century classroom . Focuses on Rigor ...",
        "productCode": "",
        "isbn10Code": "",
        "isbn13Code": "",
        "categoryid": "",
        "groupid": "",
        "publishDate": "No Date",
        "featureddate": "",
        "releasedate": "",
        "copyright": "",
        "segment": "Programs",
        "siteSection": "Education Programs",
        "contentType": "",
        "format": "",
        "publishImprints": "",
        "thumbnailImage": "/~/media/sites/home/education/disciplines/mathematics/elementary/big-ideas-math/pi-big-ideas-math.jpg",
        "lookInsideURL": "",
        "featured": "",
        "downloadURL": "",
        "weeklyRevenue": "",
        "ytdRevenue": "",
        "pages": "",
        "cartonQuantity": "",
        "newRelease": "",
        "reviews": "",
        "excerpts": "",
        "readersguideURL": "",
        "pressreleaseURL": "",
        "videoURL": "",
        "activityguideURL": "",
        "coloringpagesURL": "",
        "eventkitsURL": "",
        "shelftalkerURL": "",
        "sampleURL": "/shop/education-curriculum/math/secondary-mathematics/big-ideas-math/virtual-sampling",
        "top": "",
        "status": "",
        "series": "",
        "cpsia": "",
        "chokeHazardIndicator": "",
        "season": "",
        "jacketURL": "/~/media/sites/home/education/disciplines/mathematics/elementary/big-ideas-math/pi-big-ideas-math.jpg",
        "age": "",
        "grade": "6|7|8|9|10|11|12",
        "grade_range": "Grades 6-8,Grades 6-8,Grades 6-8,Grades 9-12,Grades 9-12,Grades 9-12,Grades 9-12",
        "grade_dd": "6|7|8|9|10|11|12",
        "grade_max": "12",
        "grade_min": "6",
        "inventoryStatus": "",
        "productType": "Program",
        "versionState": "",
        "programId": "",
        "programGroupId": "",
        "state": "",
        "restricted": "",
        "salesRestrictionCode": "",
        "componentType": "",
        "topic": "Enrichment/Support Materials,Core Curriculum",
        "versionCopyrightYear": "",
        "id": "PG0011",
        "language": "",
        "versionId": "PG00112010NATIONAL|PG00112012NATIONAL|PG00112013NATIONAL|PG00112014NATIONAL|P...",
        "programName": "",
        "buyNowUrl": "/shop/education-curriculum/math/secondary-mathematics/big-ideas-math/buy-now",
        "programsubtitle": "Middle School and High School Math",
        "programgrade": "Grades 6&#8211;12",
        "tables": {
          "authors": [],
          "formats": []
        }
      },
      {
        "index": "23",
        "url": "index:ProgramFeed?key=PG0049",
        "path": "/shop/education-curriculum/math/secondary-mathematics/holt-mcdougal-mathematics",
        "title": "Holt McDougal Mathematics",
        "metaTitle": "holt-mcdougal-mathematics",
        "subtitle": "",
        "price": "",
        "basePrice": "",
        "promoText": "",
        "desc": " A new era in the middle school math curriculum and a new approach for reaching all students! In keeping with the Common Core Standards, Holt McDougal Mathematics offers new, streamlined Student Editions that focus on deeper understanding of math strategies and concepts, with implementation of the... ",
        "body": "A new era in the middle school math curriculum and a new approach for reaching all students! In keeping with the Common Core Standards, Holt McDougal Mathematics offers new, streamlined Student Editions that focus on deeper understanding of math strategies and concepts, with implementation of the...",
        "productCode": "",
        "isbn10Code": "",
        "isbn13Code": "",
        "categoryid": "",
        "groupid": "",
        "publishDate": "No Date",
        "featureddate": "",
        "releasedate": "",
        "copyright": "",
        "segment": "Programs",
        "siteSection": "Education Programs",
        "contentType": "",
        "format": "",
        "publishImprints": "",
        "thumbnailImage": "/~/media/sites/home/education/disciplines/mathematics/elementary/holt-mcdougal-mathematics/pi-holt-mcdougal-mathematics.jpg",
        "lookInsideURL": "",
        "featured": "",
        "downloadURL": "",
        "weeklyRevenue": "",
        "ytdRevenue": "",
        "pages": "",
        "cartonQuantity": "",
        "newRelease": "",
        "reviews": "",
        "excerpts": "",
        "readersguideURL": "",
        "pressreleaseURL": "",
        "videoURL": "",
        "activityguideURL": "",
        "coloringpagesURL": "",
        "eventkitsURL": "",
        "shelftalkerURL": "",
        "sampleURL": "http://forms.hmhco.com/forms/index.php?form=vs&amp;code=na12msmcc",
        "top": "",
        "status": "",
        "series": "",
        "cpsia": "",
        "chokeHazardIndicator": "",
        "season": "",
        "jacketURL": "/~/media/sites/home/education/disciplines/mathematics/elementary/holt-mcdougal-mathematics/pi-holt-mcdougal-mathematics.jpg",
        "age": "",
        "grade": "6|7|8",
        "grade_range": "Grades 6-8,Grades 6-8,Grades 6-8",
        "grade_dd": "6|7|8",
        "grade_max": "8",
        "grade_min": "6",
        "inventoryStatus": "",
        "productType": "Program",
        "versionState": "",
        "programId": "",
        "programGroupId": "",
        "state": "",
        "restricted": "",
        "salesRestrictionCode": "",
        "componentType": "",
        "topic": "Summer School/Afterschool,Enrichment/Support Materials,Core Curriculum",
        "versionCopyrightYear": "",
        "id": "PG0049",
        "language": "",
        "versionId": "PG00492010NATIONAL|PG00492010IL|PG00492011NATIONAL|PG00492012NATIONAL|PG00492...",
        "programName": "",
        "buyNowUrl": "/shop/education-curriculum/math/secondary-mathematics/holt-mcdougal-mathematics/shop-now",
        "programsubtitle": "Middle School Math",
        "programgrade": "Grades 6&#8211;8",
        "tables": {
          "authors": [],
          "formats": []
        }
      },
      {
        "index": "24",
        "url": "index:ProgramFeed?key=PG0012",
        "path": "/shop/education-curriculum/social-studies/secondary-social-studies/civics-in-practice-principles-in-government-and-economics",
        "title": "Civics in Practice: Principles of Government and Economics",
        "metaTitle": "civics-in-practice-principles-in-government-and-economics",
        "subtitle": "",
        "price": "",
        "basePrice": "",
        "promoText": "",
        "desc": " Civics in Practice: Principles of Government and Economics &#0169; 2011 helps foster student civic responsibility through a balanced course that features the principles of government, active citizenship, and responsible economic participation. With a standards-based narrative, easy-to-navigate design, ... ",
        "body": "Civics in Practice: Principles of Government and Economics &#0169; 2011 helps foster student civic responsibility through a balanced course that features the principles of government, active citizenship, and responsible economic participation. With a standards-based narrative, easy-to-navigate design, ...",
        "productCode": "",
        "isbn10Code": "",
        "isbn13Code": "",
        "categoryid": "",
        "groupid": "",
        "publishDate": "No Date",
        "featureddate": "",
        "releasedate": "",
        "copyright": "",
        "segment": "Programs",
        "siteSection": "Education Programs",
        "contentType": "",
        "format": "",
        "publishImprints": "",
        "thumbnailImage": "/~/media/sites/home/education/disciplines/social-studies/civics/pi-civics-in-practice.jpg",
        "lookInsideURL": "",
        "featured": "",
        "downloadURL": "",
        "weeklyRevenue": "",
        "ytdRevenue": "",
        "pages": "",
        "cartonQuantity": "",
        "newRelease": "",
        "reviews": "",
        "excerpts": "",
        "readersguideURL": "",
        "pressreleaseURL": "",
        "videoURL": "",
        "activityguideURL": "",
        "coloringpagesURL": "",
        "eventkitsURL": "",
        "shelftalkerURL": "",
        "sampleURL": "http://forms.hmhco.com/forms/index.php?form=vs&amp;code=hcippige",
        "top": "",
        "status": "",
        "series": "",
        "cpsia": "",
        "chokeHazardIndicator": "",
        "season": "",
        "jacketURL": "/~/media/sites/home/education/disciplines/social-studies/civics/pi-civics-in-practice.jpg",
        "age": "",
        "grade": "7|8|9|10|11|12",
        "grade_range": "Grades 6-8,Grades 6-8,Grades 9-12,Grades 9-12,Grades 9-12,Grades 9-12",
        "grade_dd": "7|8|9|10|11|12",
        "grade_max": "12",
        "grade_min": "7",
        "inventoryStatus": "",
        "productType": "Program",
        "versionState": "",
        "programId": "",
        "programGroupId": "",
        "state": "",
        "restricted": "",
        "salesRestrictionCode": "",
        "componentType": "",
        "topic": "Enrichment/Support Materials,Core Curriculum",
        "versionCopyrightYear": "",
        "id": "PG0012",
        "language": "",
        "versionId": "PG00122009NATIONAL|PG00122012NATIONAL|PG00122011NATIONAL",
        "programName": "",
        "buyNowUrl": "/shop/education-curriculum/social-studies/secondary-social-studies/civics-in-practice-principles-in-government-and-economics/shop-now",
        "programsubtitle": "U.S. Government and Economics Curriculum",
        "programgrade": "Grades 6&#8211;12",
        "tables": {
          "authors": [],
          "formats": []
        }
      }
    ]
  }
}